{
  "0.0.1": {
    "en": "First release",
    "nl": "Eerste Release"
  },
  "0.1.0": {
    "en": "Added ovens and dishwashers",
    "nl": "Ovens en vaatwassers toegevoegd"
  },
  "0.1.1": {
    "en": "Fixed OAuth process, fixed icons on iOS devices",
    "nl": "OAuth flow gerepareerd, icoontjes op iPhones gerepareerd"
  },
  "0.1.2": {
    "en": "Added flow triggers to all supported devices",
    "nl": "Flow Triggers toegevoegd voor alle ondersteunde apparaten"
  },
  "0.1.3": {
    "en": "Added freezers, fridges, microwaves, steam-ovens and washer-dryers"
  }
}
